carbondesign/README.rst
carbondesign/__init__.py
carbondesign/apps.py
carbondesign/forms-js/fields.js
carbondesign/forms-js/forms.js
carbondesign/forms-js/widgets.js
carbondesign/js/checkbox.js
carbondesign/js/content-switcher.js
carbondesign/js/data-table.js
carbondesign/js/date-picker.js
carbondesign/js/file-uploader.js
carbondesign/js/modal.js
carbondesign/js/notification.js
carbondesign/js/overflow-menu.js
carbondesign/js/pagination.js
carbondesign/js/tabs.js
carbondesign/js/text-input.js
carbondesign/js/ui-shell.js
carbondesign/locale/id/LC_MESSAGES/django.mo
carbondesign/locale/id/LC_MESSAGES/django.po
carbondesign/locale/id/LC_MESSAGES/djangojs.mo
carbondesign/locale/id/LC_MESSAGES/djangojs.po
carbondesign/locale/jv/LC_MESSAGES/django.mo
carbondesign/locale/jv/LC_MESSAGES/django.po
carbondesign/locale/jv/LC_MESSAGES/djangojs.mo
carbondesign/locale/jv/LC_MESSAGES/djangojs.po
carbondesign/locale/su/LC_MESSAGES/django.mo
carbondesign/locale/su/LC_MESSAGES/django.po
carbondesign/locale/su/LC_MESSAGES/djangojs.mo
carbondesign/locale/su/LC_MESSAGES/djangojs.po
carbondesign/mithril-js/accordion.js
carbondesign/mithril-js/base.js
carbondesign/mithril-js/breadcrumb.js
carbondesign/mithril-js/button.js
carbondesign/mithril-js/checkbox.js
carbondesign/mithril-js/code_snippet.js
carbondesign/mithril-js/combo_box.js
carbondesign/mithril-js/content_switcher.js
carbondesign/mithril-js/copy_button.js
carbondesign/mithril-js/data-table.js
carbondesign/mithril-js/date_picker.js
carbondesign/mithril-js/dropdown.js
carbondesign/mithril-js/file_uploader.js
carbondesign/mithril-js/grid.js
carbondesign/mithril-js/hidden_input.js
carbondesign/mithril-js/inline_loading.js
carbondesign/mithril-js/link.js
carbondesign/mithril-js/list.js
carbondesign/mithril-js/list_box.js
carbondesign/mithril-js/loading.js
carbondesign/mithril-js/messages.json
carbondesign/mithril-js/modal.js
carbondesign/mithril-js/multi_select.js
carbondesign/mithril-js/notification.js
django_carbondesign-0.0.5.dist-info/LICENSE
django_carbondesign-0.0.5.dist-info/METADATA
django_carbondesign-0.0.5.dist-info/WHEEL
django_carbondesign-0.0.5.dist-info/top_level.txt
django_carbondesign-0.0.5.dist-info/RECORD
