Metadata-Version: 2.1
Name: django-carbondesign
Version: 0.0.5
Summary: Carbon Design in Django templates
Home-page: https://github.com/dozymoe/django-carbondesign
Author: Fahri Reza
Author-email: i@dozy.moe
License: MIT
Project-URL: Bug Tracker, https://github.com/dozymoe/django-carbondesign/issues
Classifier: Environment :: Web Environment
Classifier: Framework :: Django
Classifier: Intended Audience :: Developers
Classifier: License :: OSI Approved :: MIT License
Classifier: Operating System :: OS Independent
Classifier: Programming Language :: Python
Classifier: Programming Language :: Python :: 3
Classifier: Topic :: Internet :: WWW/HTTP
Classifier: Topic :: Internet :: WWW/HTTP :: Dynamic Content
License-File: LICENSE
Requires-Dist: django
Requires-Dist: lxml
Requires-Dist: pytz
